setup.cfg
setup.py
pyf/__init__.py
pyf.components.consumers.csvwriter.egg-info/PKG-INFO
pyf.components.consumers.csvwriter.egg-info/SOURCES.txt
pyf.components.consumers.csvwriter.egg-info/dependency_links.txt
pyf.components.consumers.csvwriter.egg-info/entry_points.txt
pyf.components.consumers.csvwriter.egg-info/namespace_packages.txt
pyf.components.consumers.csvwriter.egg-info/requires.txt
pyf.components.consumers.csvwriter.egg-info/top_level.txt
pyf.components.consumers.csvwriter.egg-info/zip-safe
pyf/components/__init__.py
pyf/components/consumers/__init__.py
pyf/components/consumers/csvwriter/__init__.py
pyf/components/consumers/csvwriter/addon.py
pyf/components/consumers/csvwriter/writer.py