Metadata-Version: 1.0
Name: pyf.components.consumers.csvwriter
Version: 0.3
Summary: PyF CSV Writer
Home-page: UNKNOWN
Author: UNKNOWN
Author-email: UNKNOWN
License: MIT or PSF
Platform: UNKNOWN
Classifier: Development Status :: 3 - Alpha
Classifier: Operating System :: OS Independent
Classifier: Programming Language :: Python
Classifier: License :: OSI Approved :: MIT License
Classifier: Topic :: Software Development :: Libraries :: Python Modules
